main.py
ipcflow-0.1.0.dist-info/METADATA
ipcflow-0.1.0.dist-info/WHEEL
ipcflow-0.1.0.dist-info/top_level.txt
ipcflow-0.1.0.dist-info/RECORD
